MANIFEST.in
setup.py
cask_elixir.egg-info/PKG-INFO
cask_elixir.egg-info/SOURCES.txt
cask_elixir.egg-info/dependency_links.txt
cask_elixir.egg-info/entry_points.txt
cask_elixir.egg-info/not-zip-safe
cask_elixir.egg-info/requires.txt
cask_elixir.egg-info/top_level.txt
elixir/__init__.py
elixir/app.py
elixir/controller.py
elixir/directive.py
elixir/model.py
elixir/module.py
elixir/service.py
elixir/view.py
elixir/templates/app.lxr
elixir/templates/bootstrap.lxr
elixir/templates/controller.lxr
elixir/templates/directive.lxr
elixir/templates/footer.lxr
elixir/templates/header.lxr
elixir/templates/model.lxr
elixir/templates/service.lxr
elixir/templates/view.lxr