Metadata-Version: 1.0
Name: cask-elixir
Version: 0.1.0
Summary: An AngularJS app and component generator
Home-page: http://flongular.com/elixir
Author: Zach McGrenere & Neil-the danger-Chudleigh
Author-email: zach@mcgrenere.com
License: MIT
Platform: UNKNOWN
